Metadata-Version: 2.1
Name: jk-cachefunccalls
Version: 0.2020.3.5.1
Summary: This python module provides an annotation that caches results of function calls automatically.
Home-page: https://github.com/jkpubsrc/python-module-jk-cachefunccalls
Author: Jürgen Knauth
Author-email: pubsrc@binary-overflow.de
License: Apache 2.0
Download-URL: https://github.com/jkpubsrc/python-module-jk-cachefunccalls/tarball/0.2020.3.5.1
Keywords: caching
Platform: UNKNOWN
Classifier: Development Status :: 3 - Alpha
Classifier: License :: OSI Approved :: Apache Software License
